lgpt/.env
lgpt/__init__.py
lgpt/lgpt.py
lgpt/utils/__init__.py
lgpt/utils/__version__.py
lgpt/utils/get_path.py
lgpt/utils/handle_data.py
lgpt/utils/lgpt_updater.py
lgpt/utils/llms_handler.py
lgpt/utils/load_env_datas.py
lgpt/utils/markdown_handler.py
lgpt/utils/models.py
lgpt/utils/utils.py
lgpt/utils/version_controller.py
linux_gpt-1.3.2.dist-info/licenses/LICENSE
linux_gpt-1.3.2.dist-info/METADATA
linux_gpt-1.3.2.dist-info/WHEEL
linux_gpt-1.3.2.dist-info/entry_points.txt
linux_gpt-1.3.2.dist-info/top_level.txt
linux_gpt-1.3.2.dist-info/RECORD
