Metadata-Version: 2.4
Name: linux-gpt
Version: 1.3.2
Summary: An elite terminal-based assistant for Linux developers, security engineers, and ethical hackers.
Home-page: https://github.com/AmianDevSec/lgpt
Author: AmianDevSec
Author-email: amiandevsec@gmail.com
License: GPL-3.0-only
Classifier: Programming Language :: Python :: 3
Classifier: License :: OSI Approved :: GNU General Public License v3 (GPLv3)
Classifier: Operating System :: POSIX :: Linux
Classifier: Intended Audience :: Developers
Classifier: Topic :: Security
Requires-Python: >=3.7
License-File: LICENSE
Requires-Dist: python-dotenv
Requires-Dist: packaging
Requires-Dist: requests
Dynamic: author
Dynamic: author-email
Dynamic: classifier
Dynamic: home-page
Dynamic: license
Dynamic: license-file
Dynamic: requires-dist
Dynamic: requires-python
Dynamic: summary
